{
	"openapi": "3.0.2",
	"info": {
		"title": "Order Service - OpenAPI 3.0",
		"description": "Order Service based on the OpenAPI 3.0 specification. You can find out more about Swagger at [http://swagger.io](http://swagger.io)",
		"termsOfService": "http://swagger.io/terms/",
		"contact": {
			"email": "apiteam@swagger.io"
		},
		"license": {
			"name": "Apache 2.0",
			"url": "http://www.apache.org/licenses/LICENSE-2.0.html"
		},
		"version": "1.0.0"
	},
	"externalDocs": {
		"description": "Find out more about Swagger",
		"url": "http://swagger.io"
	},
	"servers": [
		{
			"url": "{scheme}://{host}/{basePath}",
			"variables": {
				"scheme": {
					"enum": [
						"https",
						"http"
					],
					"default": "https"
				},
				"host": {
					"default": "order-service.example.com"
				},
				"basePath": {
					"default": "/api/v1"
				}
			}
		}
	],
	"tags": [
		{
			"name": "order",
			"description": "Operations related to orders"
		}
	],
	"paths": {
		"/order": {
			"post": {
				"tags": [
					"order"
				],
				"summary": "Place a new order",
				"description": "Create a new order",
				"operationId": "placeOrder",
				"requestBody": {
					"description": "Order details",
					"required": true,
					"content": {
						"application/json": {
							"schema": {
								"$ref": "#/components/schemas/Order"
							}
						}
					}
				},
				"responses": {
					"200": {
						"description": "Successful operation",
						"content": {
							"application/json": {
								"schema": {
									"$ref": "#/components/schemas/Order"
								}
							}
						}
					},
					"400": {
						"description": "Bad request"
					},
					"500": {
						"description": "Internal server error"
					}
				}
			}
		}
	},
	"components": {
		"schemas": {
			"Order": {
				"type": "object",
				"properties": {
					"id": {
						"type": "integer",
						"format": "int64"
					},
					"customerId": {
						"type": "integer",
						"format": "int64"
					},
					"items": {
						"type": "array",
						"items": {
							"type": "object",
							"properties": {
								"productId": {
									"type": "integer",
									"format": "int64"
								},
								"quantity": {
									"type": "integer",
									"format": "int32"
								}
							}
						}
					},
					"status": {
						"type": "string",
						"enum": [
							"placed",
							"processing",
							"shipped",
							"delivered",
							"cancelled"
						]
					},
					"createdAt": {
						"type": "string",
						"format": "date-time"
					},
					"updatedAt": {
						"type": "string",
						"format": "date-time"
					}
				}
			}
		}
	}
}
